maestros/__init__.py
maestros/functions.py
maestros-0.1.1.dist-info/LICENSE
maestros-0.1.1.dist-info/METADATA
maestros-0.1.1.dist-info/WHEEL
maestros-0.1.1.dist-info/top_level.txt
maestros-0.1.1.dist-info/RECORD
